memorybuffer/__about__.py
memorybuffer/__init__.py
memorybuffer/_memorybuffer.py
memorybuffer/_platform.py
memorybuffer/_typeobject.py
memorybuffer-0.7.0b1.dist-info/LICENSE
memorybuffer-0.7.0b1.dist-info/METADATA
memorybuffer-0.7.0b1.dist-info/WHEEL
memorybuffer-0.7.0b1.dist-info/top_level.txt
memorybuffer-0.7.0b1.dist-info/zip-safe
memorybuffer-0.7.0b1.dist-info/RECORD
