Metadata-Version: 2.1
Name: memorybuffer
Version: 0.7.0b1
Summary: Python buffer protocol.
Author: Adam Karpierz
Author-email: adam@karpierz.net
Maintainer: Adam Karpierz
Maintainer-email: adam@karpierz.net
License: zlib/libpng License ; https://opensource.org/license/zlib
Project-URL: Homepage, https://pypi.org/project/memorybuffer/
Project-URL: Documentation, https://memorybuffer.readthedocs.io/
Project-URL: Download, https://pypi.org/project/memorybuffer/
Project-URL: Source, https://github.com/karpierz/memorybuffer
Project-URL: Issues, https://github.com/karpierz/memorybuffer/issues
Keywords: memorybuffer,memoryview,buffer
Platform: any
Classifier: Development Status :: 5 - Production/Stable
Classifier: Intended Audience :: Developers
Classifier: License :: OSI Approved :: zlib/libpng License
Classifier: Operating System :: OS Independent
Classifier: Natural Language :: Polish
Classifier: Programming Language :: Python
Classifier: Programming Language :: Python :: 3
Classifier: Programming Language :: Python :: 3.9
Classifier: Programming Language :: Python :: 3.10
Classifier: Programming Language :: Python :: 3.11
Classifier: Programming Language :: Python :: 3.12
Classifier: Programming Language :: Python :: 3.13
Classifier: Programming Language :: Python :: 3 :: Only
Classifier: Programming Language :: Python :: Implementation :: CPython
Classifier: Programming Language :: Python :: Implementation :: PyPy
Classifier: Topic :: Software Development :: Libraries :: Python Modules
Requires-Python: <4.0.0,>=3.9.0
License-File: LICENSE
Requires-Dist: setuptools>=75.3.0
Requires-Dist: pkg-about>=1.2.2
Provides-Extra: doc
Requires-Dist: Sphinx>=7.4.7; extra == "doc"
Requires-Dist: sphinx-toolbox>=3.8.1; extra == "doc"
Requires-Dist: sphinx-tabs>=3.4.5; extra == "doc"
Requires-Dist: sphinx-copybutton>=0.5.2; extra == "doc"
Requires-Dist: sphinxcontrib-spelling>=8.0.0; extra == "doc"
Requires-Dist: sphinx-lint>=1.0.0; extra == "doc"
Requires-Dist: restructuredtext-lint>=1.4.0; extra == "doc"
Requires-Dist: nbsphinx>=0.9.5; extra == "doc"
Provides-Extra: test
Requires-Dist: deepdiff>=8.0.1; extra == "test"
Requires-Dist: rich>=13.9.4; extra == "test"
